{
  "LST_ancillary_ds.nc:LST_uncertainty_locATM": "/quality/lst_uncertainty_atm",
  "LST_ancillary_ds.nc:LST_uncertainty_locATM_orphan": "/quality/orphan/lst_uncertainty_atm",
  "LST_ancillary_ds.nc:LST_uncertainty_locGEO": "/quality/lst_uncertainty_geo",
  "LST_ancillary_ds.nc:LST_uncertainty_locGEO_orphan": "/quality/orphan/lst_uncertainty_geo",
  "LST_ancillary_ds.nc:LST_uncertainty_locSF": "/quality/lst_uncertainty_sf",
  "LST_ancillary_ds.nc:LST_uncertainty_locSF_orphan": "/quality/orphan/lst_uncertainty_sf",
  "LST_ancillary_ds.nc:LST_uncertainty_locT": "/quality/lst_uncertainty_t",
  "LST_ancillary_ds.nc:LST_uncertainty_locT_orphan": "/quality/orphan/lst_uncertainty_t",
  "LST_ancillary_ds.nc:LST_uncertainty_random": "/quality/lst_uncertainty_random",
  "LST_ancillary_ds.nc:LST_uncertainty_random_orphan": "/quality/orphan/lst_uncertainty_random",
  "LST_ancillary_ds.nc:LST_uncertainty_sys": "/quality/lst_uncertainty_sys",
  "LST_ancillary_ds.nc:LST_uncertainty_sys_orphan": "/quality/orphan/lst_uncertainty_sys",
  "LST_ancillary_ds.nc:NDVI": "/conditions/auxiliary/ndvi",
  "LST_ancillary_ds.nc:NDVI_orphan": "/conditions/auxiliary/orphan/ndvi",
  "LST_ancillary_ds.nc:TCWV": "/conditions/auxiliary/tcwv",
  "LST_ancillary_ds.nc:TCWV_orphan": "/conditions/auxiliary/orphan/tcwv",
  "LST_ancillary_ds.nc:biome": "/conditions/auxiliary/biome",
  "LST_ancillary_ds.nc:biome_orphan": "/conditions/auxiliary/orphan/biome",
  "LST_ancillary_ds.nc:fraction": "/conditions/auxiliary/fraction",
  "LST_ancillary_ds.nc:fraction_orphan": "/conditions/auxiliary/orphan/fraction",
  "LST_ancillary_ds.nc:validation": "/conditions/auxiliary/validation",
  "LST_in.nc:LST": "/measurements/lst",
  "LST_in.nc:LST_orphan": "/measurements/orphan/lst",
  "LST_in.nc:LST_uncertainty": "/quality/lst_uncertainty",
  "LST_in.nc:LST_uncertainty_orphan": "/quality/orphan/lst_uncertainty",
  "LST_in.nc:exception": "/quality/exception",
  "LST_in.nc:exception_orphan": "/quality/orphan/exception",
  "cartesian_in.nc:columns": "coords:columns_in",
  "cartesian_in.nc:orphan_pixels": "coords:orphan_pixels_in",
  "cartesian_in.nc:rows": "coords:rows_in",
  "cartesian_in.nc:x_in": "coords:x_in",
  "cartesian_in.nc:x_orphan_in": "coords:x_orphan_in",
  "cartesian_in.nc:y_in": "coords:y_in",
  "cartesian_in.nc:y_orphan_in": "coords:y_orphan_in",
  "cartesian_tx.nc:columns": "coords:columns_tp",
  "cartesian_tx.nc:rows": "coords:rows_tp",
  "cartesian_tx.nc:x_tx": "coords:x_tp",
  "cartesian_tx.nc:y_tx": "coords:y_tp",
  "flags_in.nc:cloud_in": "/quality/cloud_in",
  "flags_in.nc:cloud_orphan_in": "/quality/orphan/cloud_orphan_in",
  "flags_in.nc:confidence_in": "/quality/confidence_in",
  "flags_in.nc:confidence_orphan_in": "/quality/orphan/confidence_orphan_in",
  "flags_in.nc:pointing_in": "/quality/pointing_in",
  "flags_in.nc:pointing_orphan_in": "/quality/orphan/pointing_orphan_in",
  "geodetic_in.nc:elevation_in": "/conditions/auxiliary/elevation",
  "geodetic_in.nc:elevation_orphan_in": "/conditions/auxiliary/orphan/elevation",
  "geodetic_in.nc:latitude_in": "coords:latitude_in",
  "geodetic_in.nc:latitude_orphan_in": "coords:latitude_orphan_in",
  "geodetic_in.nc:longitude_in": "coords:longitude_in",
  "geodetic_in.nc:longitude_orphan_in": "coords:longitude_orphan_in",
  "geodetic_tx.nc:latitude_tx": "coords:latitude_tp",
  "geodetic_tx.nc:longitude_tx": "coords:longitude_tp",
  "geometry_tn.nc:columns": "coords:columns_tn",
  "geometry_tn.nc:rows": "coords:rows_tn",
  "geometry_tn.nc:sat_azimuth_tn": "/conditions/geometry/sat_azimuth_tn",
  "geometry_tn.nc:sat_path_tn": "/conditions/geometry/sat_path_tn",
  "geometry_tn.nc:sat_zenith_tn": "/conditions/geometry/sat_zenith_tn",
  "geometry_tn.nc:solar_azimuth_tn": "/conditions/geometry/solar_azimuth_tn",
  "geometry_tn.nc:solar_path_tn": "/conditions/geometry/solar_path_tn",
  "geometry_tn.nc:solar_zenith_tn": "/conditions/geometry/solar_zenith_tn",
  "indices_in.nc:detector_in": "/conditions/processing/detector",
  "indices_in.nc:detector_orphan_in": "/conditions/processing/orphan/detector",
  "indices_in.nc:pixel_in": "/conditions/processing/pixel",
  "indices_in.nc:pixel_orphan_in": "/conditions/processing/orphan/pixel",
  "indices_in.nc:scan_in": "/conditions/processing/scan",
  "indices_in.nc:scan_orphan_in": "/conditions/processing/orphan/scan",
  "met_tx.nc:cloud_fraction_tx": "/conditions/meteorology/cloud_fraction_tp",
  "met_tx.nc:dew_point_tx": "/conditions/meteorology/dew_point_tp",
  "met_tx.nc:east_west_stress_tx": "/conditions/meteorology/east_west_stress_tp",
  "met_tx.nc:latent_heat_tx": "/conditions/meteorology/latent_heat_tp",
  "met_tx.nc:north_south_stress_tx": "/conditions/meteorology/north_south_stress_tp",
  "met_tx.nc:p_atmos": "coords:p_atmos",
  "met_tx.nc:sea_ice_fraction_tx": "/conditions/meteorology/sea_ice_fraction_tp",
  "met_tx.nc:sea_surface_temperature_tx": "/conditions/meteorology/sea_surface_temperature_tp",
  "met_tx.nc:sensible_heat_tx": "/conditions/meteorology/sensible_heat_tp",
  "met_tx.nc:skin_temperature_tx": "/conditions/meteorology/skin_temperature_tp",
  "met_tx.nc:snow_albedo_tx": "/conditions/meteorology/snow_albedo_tp",
  "met_tx.nc:snow_depth_tx": "/conditions/meteorology/snow_depth_tp",
  "met_tx.nc:soil_wetness_tx": "/conditions/meteorology/soil_wetness_tp",
  "met_tx.nc:solar_radiation_tx": "/conditions/meteorology/solar_radiation_tp",
  "met_tx.nc:specific_humidity_tx": "/conditions/meteorology/specific_humidity_tp",
  "met_tx.nc:surface_pressure_tx": "/conditions/meteorology/surface_pressure_tp",
  "met_tx.nc:t_series": "coords:t_series",
  "met_tx.nc:temperature_profile_tx": "/conditions/meteorology/temperature_profile_tp",
  "met_tx.nc:temperature_tx": "/conditions/meteorology/temperature_tp",
  "met_tx.nc:thermal_radiation_tx": "/conditions/meteorology/thermal_radiation_tp",
  "met_tx.nc:total_column_ozone_tx": "/conditions/meteorology/total_column_ozone_tp",
  "met_tx.nc:total_column_water_vapour_tx": "/conditions/meteorology/total_column_water_vapour_tp",
  "met_tx.nc:u_wind_tx": "/conditions/meteorology/u_wind_tp",
  "met_tx.nc:v_wind_tx": "/conditions/meteorology/v_wind_tp",
  "time_in.nc:Nadir_First_scan_i": "/conditions/time/nadir_first_scan_i",
  "time_in.nc:Nadir_Last_scan_i": "/conditions/time/nadir_last_scan_i",
  "time_in.nc:Nadir_Maximal_ts_i": "/conditions/time/nadir_maximal_ts_i",
  "time_in.nc:Nadir_Minimal_ts_i": "/conditions/time/nadir_minimal_ts_i",
  "time_in.nc:Oblique_First_scan_i": "/conditions/time/oblique_first_scan_i",
  "time_in.nc:Oblique_Last_scan_i": "/conditions/time/oblique_last_scan_i",
  "time_in.nc:Oblique_Maximal_ts_i": "/conditions/time/oblique_maximal_ts_i",
  "time_in.nc:Oblique_Minimal_ts_i": "/conditions/time/oblique_minimal_ts_i",
  "time_in.nc:time_stamp_i": "/conditions/time/time_stamp_i"
}
